baimi/datasource/vecdb/VecDb.py
baimi/datasource/vecdb/VecDbCcrcyTest.py
baimi/datasource/vecdb/VecDbSingleton.py
baimi/datasource/vecdb/VecDbUnitTest.py
baimi/datasource/vecdb/metadata/Metadata.py
baimi/datasource/vecdb/model/ModelDb.py
baimi/datasource/vecdb/model/UnitTest.py
baimi-0.0.1.dist-info/LICENSE
baimi-0.0.1.dist-info/METADATA
baimi-0.0.1.dist-info/WHEEL
baimi-0.0.1.dist-info/top_level.txt
baimi-0.0.1.dist-info/RECORD
