Metadata-Version: 2.1
Name: baimi
Version: 0.0.1
Summary: Vector DB
Author: MM
Classifier: Programming Language :: Python :: 3
Classifier: License :: OSI Approved :: MIT License
Classifier: Operating System :: OS Independent
Requires-Python: <=3.12,>=3.9
License-File: LICENSE
Requires-Dist: matplotlib>=3.0.0
Requires-Dist: networkx
Requires-Dist: numpy>=1.20.0
Requires-Dist: pandas>=2.0.0
Requires-Dist: scikit-learn>=1.2.0
Requires-Dist: torch>=2.0.0
Requires-Dist: pillow
